mrtrix3_agent-1.0.14.dist-info/licenses/LICENSE
src/__init__.py
src/__main__.py
src/agent/__init__.py
src/agent/__main__.py
src/agent/agent.py
src/agent/async_dependencies.py
src/agent/cache.py
src/agent/circuit_breaker.py
src/agent/cli.py
src/agent/config.py
src/agent/dependencies.py
src/agent/embedding_service.py
src/agent/error_messages.py
src/agent/local_storage_manager.py
src/agent/markdown_fixer.py
src/agent/models.py
src/agent/monitoring_integration.py
src/agent/rate_limiter.py
src/agent/schema_migrations.py
src/agent/session_logger.py
src/agent/setup_config.py
src/agent/slash_commands.py
src/agent/storage_info.py
src/agent/sync_manager.py
src/agent/tools.py
src/agent/validate_setup.py
src/knowledge_base/__init__.py
src/knowledge_base/error_extractor.py
src/knowledge_base/generate_embeddings.py
src/knowledge_base/populate_database.py
src/workflows/__init__.py
src/workflows/sharefile/__init__.py
src/workflows/sharefile/sharefile.py
mrtrix3_agent-1.0.14.dist-info/METADATA
mrtrix3_agent-1.0.14.dist-info/WHEEL
mrtrix3_agent-1.0.14.dist-info/entry_points.txt
mrtrix3_agent-1.0.14.dist-info/top_level.txt
mrtrix3_agent-1.0.14.dist-info/RECORD
