Metadata-Version: 2.4
Name: mrtrix3-agent
Version: 1.0.14
Summary: MRtrix3 AI Agent
Author-email: Robert Moskwa <rmoskwa@wisc.edu>
License: MIT
Classifier: Programming Language :: Python :: 3
Classifier: Programming Language :: Python :: 3.10
Classifier: Programming Language :: Python :: 3.11
Classifier: Programming Language :: Python :: 3.12
Classifier: License :: OSI Approved :: MIT License
Classifier: Operating System :: OS Independent
Requires-Python: >=3.10
License-File: LICENSE
Requires-Dist: supabase>=2.0.0
Requires-Dist: google-generativeai>=0.3.0
Requires-Dist: pydantic-ai>=0.0.1
Requires-Dist: pydantic>=2.0.0
Requires-Dist: python-dotenv>=1.0.0
Requires-Dist: rich>=13.0.0
Requires-Dist: tenacity>=8.0.0
Requires-Dist: chromadb>=1.0.0
Requires-Dist: psutil>=5.9.0
Requires-Dist: pyfiglet>=1.0.0
Requires-Dist: platformdirs>=3.0.0
Provides-Extra: dev
Requires-Dist: pytest>=7.4.0; extra == "dev"
Requires-Dist: pytest-asyncio>=0.21.0; extra == "dev"
Requires-Dist: pytest-cov>=4.1.0; extra == "dev"
Dynamic: license-file
